VGenEval/__init__.py
VGenEval/load_prompt.py
VGenEval-0.1.0.dist-info/LICENSE.txt
VGenEval-0.1.0.dist-info/METADATA
VGenEval-0.1.0.dist-info/WHEEL
VGenEval-0.1.0.dist-info/top_level.txt
VGenEval-0.1.0.dist-info/RECORD
