Metadata-Version: 2.1
Name: VGenEval
Version: 0.1.0
Summary: A package for loading prompts for video generation evaluation
Home-page: https://github.com/AILab-CVC/VideoGen-Eval
Author: Yuhang Yang
Author-email: yangyuhang.edu@gmail.com
License: UNKNOWN
Platform: UNKNOWN
Classifier: Programming Language :: Python :: 3
Classifier: License :: OSI Approved :: MIT License
Classifier: Operating System :: OS Independent
Requires-Python: >=3.6
License-File: LICENSE.txt
Requires-Dist: pandas
Requires-Dist: numpy
